odoo/addons/sale_stock_delivery_address/README.rst
odoo/addons/sale_stock_delivery_address/__init__.py
odoo/addons/sale_stock_delivery_address/__manifest__.py
odoo/addons/sale_stock_delivery_address/i18n/ca.po
odoo/addons/sale_stock_delivery_address/i18n/es.po
odoo/addons/sale_stock_delivery_address/i18n/it.po
odoo/addons/sale_stock_delivery_address/i18n/sale_stock_delivery_address.pot
odoo/addons/sale_stock_delivery_address/models/__init__.py
odoo/addons/sale_stock_delivery_address/models/procurement_group.py
odoo/addons/sale_stock_delivery_address/models/sale_order_line.py
odoo/addons/sale_stock_delivery_address/readme/CONTRIBUTORS.md
odoo/addons/sale_stock_delivery_address/readme/DESCRIPTION.md
odoo/addons/sale_stock_delivery_address/readme/USAGE.md
odoo/addons/sale_stock_delivery_address/static/description/icon.png
odoo/addons/sale_stock_delivery_address/static/description/img_rule.png
odoo/addons/sale_stock_delivery_address/static/description/img_transfers_01.png
odoo/addons/sale_stock_delivery_address/static/description/img_transfers_02.png
odoo/addons/sale_stock_delivery_address/static/description/index.html
odoo/addons/sale_stock_delivery_address/static/description/partner_locations.gif
odoo/addons/sale_stock_delivery_address/static/description/sale_order_destination_address.gif
odoo/addons/sale_stock_delivery_address/static/description/source_location.png
odoo/addons/sale_stock_delivery_address/tests/__init__.py
odoo/addons/sale_stock_delivery_address/tests/common.py
odoo/addons/sale_stock_delivery_address/tests/test_sale_stock_delivery_address.py
odoo/addons/sale_stock_delivery_address/views/res_partner_view.xml
odoo/addons/sale_stock_delivery_address/views/sale_order_view.xml
odoo_addon_sale_stock_delivery_address-18.0.1.1.1.dist-info/METADATA
odoo_addon_sale_stock_delivery_address-18.0.1.1.1.dist-info/WHEEL
odoo_addon_sale_stock_delivery_address-18.0.1.1.1.dist-info/top_level.txt
odoo_addon_sale_stock_delivery_address-18.0.1.1.1.dist-info/RECORD
