Metadata-Version: 2.1
Name: odoo-addon-sale_stock_delivery_address
Version: 18.0.1.1.1
Requires-Python: >=3.10
Requires-Dist: odoo-addon-sale_procurement_group_by_line==18.0.*
Requires-Dist: odoo==18.0.*
Summary: Sale Stock Delivery Address
Home-page: https://github.com/OCA/sale-workflow
License: AGPL-3
Author: ForgeFlow, Odoo Community Association (OCA)
Author-email: support@odoo-community.org
Classifier: Programming Language :: Python
Classifier: Framework :: Odoo
Classifier: Framework :: Odoo :: 18.0
Classifier: License :: OSI Approved :: GNU Affero General Public License v3
Classifier: Development Status :: 5 - Production/Stable
